advocate/__init__.py
advocate/adapters.py
advocate/addrvalidator.py
advocate/api.py
advocate/connection.py
advocate/connectionpool.py
advocate/exceptions.py
advocate/futures.py
advocate/poolmanager.py
advocate/packages/__init__.py
advocate/packages/ipaddress/__init__.py
advocate/packages/ipaddress/ipaddress.py
advocate-1.0.0.dist-info/LICENSE
advocate-1.0.0.dist-info/METADATA
advocate-1.0.0.dist-info/WHEEL
advocate-1.0.0.dist-info/top_level.txt
advocate-1.0.0.dist-info/RECORD
