Metadata-Version: 1.1
Name: advocate
Version: 1.0.0
Summary: A wrapper around the requests library for safely making HTTP requests on behalf of a third party
Home-page: https://github.com/JordanMilne/Advocate
Author: Jordan Milne
Author-email: advocate@saynotolinux.com
License: Apache 2
Keywords: http requests security ssrf proxy rebinding advocate
Platform: UNKNOWN
Classifier: Development Status :: 4 - Beta
Classifier: Intended Audience :: Developers
Classifier: Natural Language :: English
Classifier: License :: OSI Approved :: Apache Software License
Classifier: Programming Language :: Python
Classifier: Programming Language :: Python :: 2.7
Classifier: Programming Language :: Python :: 3.6
Classifier: Programming Language :: Python :: 3.7
Classifier: Programming Language :: Python :: 3.8
Classifier: Topic :: Security
Classifier: Topic :: Internet :: WWW/HTTP
